lib/SimpleSC.py
lib/__init__.py
SimpleSC-0.0.1.dist-info/METADATA
SimpleSC-0.0.1.dist-info/WHEEL
SimpleSC-0.0.1.dist-info/top_level.txt
SimpleSC-0.0.1.dist-info/RECORD
