Metadata-Version: 2.1
Name: SimpleSC
Version: 0.0.1
Summary: Creating a Server And Client easily
Home-page: UNKNOWN
Author: The Vast(youtuber, INDIA)
Author-email: <thevastofficial2021@gmail.com>
License: UNKNOWN
Keywords: python3,sockets
Platform: UNKNOWN
Classifier: Development Status :: 1 - Planning
Classifier: Intended Audience :: Developers
Classifier: Programming Language :: Python :: 3
Classifier: Operating System :: Unix
Classifier: Operating System :: MacOS :: MacOS X
Classifier: Operating System :: Microsoft :: Windows
